<?xml version="1.0" encoding="UTF-8"?>
<artist>
  <name>Monty Python</name>
  <albums>
    <album>Always Look On The Bright Side Of Life (The Unofficial England Football Anthem)</album>
    <album>Concert For George (Live)</album>
    <album>Hits from the Movies</album>
    <album>Live At Drury Lane</album>
    <album>Monty Python Sings</album>
    <album>Monty Python Sings (Again)</album>
    <album>Monty Python's Contractual Obligation Album</album>
    <album>Monty Python's Life Of Brian (Original Motion Picture Soundtrack)</album>
    <album>Monty Python's Previous Record</album>
    <album>Monty Python's Total Rubbish! The (Mostly) Charisma Collection</album>
    <album>Stephen Hawking Sings Monty Python… Galaxy Song</album>
    <album>The Album Of The Soundtrack Of The Trailer Of The Film Of Monty Python And The Holy Grail</album>
    <album>The Meaning Of Life</album>
    <album>The Ultimate Monty Python Rip Off</album>
  </albums>
</artist>