<?xml version="1.0" encoding="UTF-8"?>
<artist>
  <name>Kate Ryan</name>
  <albums>
    <album>Alive</album>
    <album>Broken</album>
    <album>Broken (International Release)</album>
    <album>Casser la voix</album>
    <album>Chiringuito Mix</album>
    <album>Comment Te Dire Adieu</album>
    <album>Covered In Dance (your Favorite Hits Remixed In Dance)</album>
    <album>Désenchantée</album>
    <album>Different</album>
    <album>Electroshock</album>
    <album>Ella Elle L'a</album>
    <album>Essential</album>
    <album>Free</album>
    <album>I Surrender</album>
    <album>Kate Ryan - Babacar</album>
    <album>Kate Ryan - French Connection</album>
    <album>Runaway (Smalltown Boy) (Remixes)</album>
    <album>Runaway [Smalltown Boy]</album>
    <album>Runaway [Smalltown Boy] (Antrox Remix)</album>
    <album>Runaway [Smalltown Boy] (Remixes)</album>
    <album>Stronger</album>
    <album>The Promise</album>
    <album>Voyage Voyage</album>
    <album>Wonderful Life</album>
  </albums>
</artist>