<?xml version="1.0" encoding="UTF-8"?>
<artist>
  <name>King Diamond</name>
  <albums>
    <album>20 Years Ago - A Night of Rehearsal</album>
    <album>Abigail</album>
    <album>Abigail II - The Revenge</album>
    <album>Blood My Side (Deluxe Edition)</album>
    <album>Conspiracy</album>
    <album>Deadly Lullabyes (Live)</album>
    <album>Dreams of Horror</album>
    <album>Fatal Portrait</album>
    <album>Give Me Your Soul...Please</album>
    <album>House of God</album>
    <album>In Concert 1987- Abigail (Live)</album>
    <album>In Concert 1987: Abigail (Live)</album>
    <album>Lost Soul Classics</album>
    <album>Masquerade of Madness</album>
    <album>Songs for the Dead- Live at Graspop Metal Meeting</album>
    <album>Songs for the Dead- Live at the Fillmore in Philadelphia</album>
    <album>Songs for the Dead: Live at Graspop Metal Meeting</album>
    <album>Songs for the Dead: Live at the Fillmore in Philadelphia</album>
    <album>Spider Lilly</album>
    <album>The Dark Sides</album>
    <album>The Eye</album>
    <album>The Graveyard</album>
    <album>The Puppet Master</album>
    <album>The Spider's Lullabye</album>
    <album>Them</album>
    <album>Voodoo</album>
  </albums>
</artist>