<?xml version="1.0" encoding="UTF-8"?>
<artist>
  <name>Sneaker Pimps</name>
  <albums>
    <album>6 Underground</album>
  <album>6 Underground</album>
  <album>Becoming Remixed</album>
  <album>Becoming Remixed</album>
  <album>Becoming X</album>
  <album>Becoming X</album>
  <album>Bloodsport</album>
  <album>Bloodsport</album>
  <album>Post Modern Sleaze</album>
  <album>Post Modern Sleaze</album>
  <album>Splinter</album>
  <album>Splinter</album>
  <album>Squaring The Circle</album>
  <album>Squaring The Circle</album>
  </albums>
</artist>