<?xml version="1.0" encoding="UTF-8"?>
<artist>
  <name>James Moody</name>
  <albums>
    <album>All the Best</album>
    <album>Amy Winehouse's Jukebox</album>
    <album>At the Jazz Workshop</album>
    <album>At The Jazz Workshop</album>
    <album>Autumn Leaves</album>
    <album>Bop in the Breeze</album>
    <album>Brother Yusef</album>
    <album>Complete Jazz Series 1951</album>
    <album>Don't Look Away Now!</album>
    <album>Embraceable You</album>
    <album>Feelin' It Together</album>
    <album>Golden Hits By James Moody</album>
    <album>Hey! It's James Moody</album>
    <album>Hey!, It's James Moody + Flute 'N the Blues (Bonus Track Version)</album>
    <album>In the Mood for Love</album>
    <album>James Moody</album>
    <album>Jazz At The Philharmonic In London, 1969</album>
    <album>Jazz Workshop</album>
    <album>Just Moody</album>
    <album>Last Train from Overbrook</album>
    <album>Last Train From Overbrook</album>
    <album>Loose & Juicy</album>
    <album>Moody 4A</album>
    <album>Moody Flooty</album>
    <album>Moody With Strings</album>
    <album>Moody's Groove</album>
    <album>Moody's Mood for Love</album>
    <album>Moody's Mood For Love</album>
    <album>Moody's Mood for Love (Remastered)</album>
    <album>Our Delight</album>
    <album>Saxophone Serenade</album>
    <album>The Best Vintage Selection - James Moody</album>
    <album>The Complete Argo Collection</album>
    <album>The Essential Tracks</album>
    <album>The Music Of Richard Rodgers</album>
    <album>The Ultimate Jazz Archive 27 - 1951 - 55 (1 Of 4)</album>
    <album>The Very Best Of Prestige Records (60th Anniversary)</album>
    <album>There She Goes</album>
    <album>Top 100 Classics - The Very Best of James Moody</album>
    <album>Wave (Live Remastered)</album>
  </albums>
</artist>