<?xml version="1.0" encoding="UTF-8"?>
<artist>
  <name>Trick Daddy</name>
  <albums>
    <album>1990 Until...</album>
    <album>2000s Hip Hop Hits</album>
    <album>Any Given Sunday (Original Soundtrack)</album>
    <album>Back by Thug Demand</album>
    <album>Based On A True Story</album>
    <album>Book of Thugs: Chapter AK Verse 47</album>
    <album>Class of 2004</album>
    <album>Got Your Money - Rap Classics</album>
    <album>Let's Go</album>
    <album>Paradise (feat. Mike Smiff)</album>
    <album>Sugar (Gimme Some)</album>
    <album>Thug Holiday (Explicit Version)</album>
    <album>Thug Matrimony: Married to the Streets</album>
    <album>THUGS ARE US</album>
    <album>www.thug.com</album>
  </albums>
</artist>