<?xml version="1.0" encoding="UTF-8"?>
<artist>
  <name>Felt</name>
  <albums>
    <album>Absolute Classic Masterpieces</album>
    <album>Air Textures</album>
    <album>Bubblegum Perfume</album>
    <album>Cali Roots Riddim 2021</album>
    <album>Crumbling the Antiseptic Beauty (Remastered Edition)</album>
    <album>Forever Breathes the Lonely Word</album>
    <album>Forever Breathes the Lonely Word (Remastered Edition)</album>
    <album>Ignite the Seven Cannons (Remastered Edition)</album>
    <album>Jazz Funk</album>
    <album>Poem of the River</album>
    <album>Split Particles</album>
    <album>The Seventeenth Century (Remastered Edition)</album>
    <album>The Strange Idols Pattern and Other Short Stories (Remastered Edition)</album>
  </albums>
</artist>