<?xml version="1.0" encoding="UTF-8"?>
<artist>
  <name>Manic Street Preachers</name>
  <albums>
    <album>Critical Thinking</album>
  <album>Critical Thinking</album>
  <album>Everything Must Go 10th Anniversary Edition</album>
  <album>Everything Must Go 10th Anniversary Edition</album>
  <album>Everything Must Go 20 (Remastered)</album>
  <album>Everything Must Go 20 (Remastered)</album>
  <album>Forever Delayed</album>
  <album>Forever Delayed</album>
  <album>Futurology (Deluxe)</album>
  <album>Futurology (Deluxe)</album>
  <album>GENERATION TERRORISTS</album>
  <album>GENERATION TERRORISTS</album>
  <album>GOLD AGAINST THE SOUL</album>
  <album>GOLD AGAINST THE SOUL</album>
  <album>Gold Against the Soul (Remastered)</album>
  <album>Gold Against the Soul (Remastered)</album>
  <album>Journal For Plague Lovers</album>
  <album>Journal For Plague Lovers</album>
  <album>Journal For Plague Lovers Remixes</album>
  <album>Journal For Plague Lovers Remixes</album>
  <album>Know Your Enemy</album>
  <album>Know Your Enemy</album>
  <album>Lifeblood</album>
  <album>Lifeblood</album>
  <album>National Treasures - The Complete Singles</album>
  <album>National Treasures - The Complete Singles</album>
  <album>Postcards From A Young Man</album>
  <album>Postcards From A Young Man</album>
  <album>Resistance Is Futile (Deluxe)</album>
  <album>Resistance Is Futile (Deluxe)</album>
  <album>Rewind the Film</album>
  <album>Rewind the Film</album>
  <album>Send Away The Tigers</album>
  <album>Send Away The Tigers</album>
  <album>The Holy Bible 20 (Remastered)</album>
  <album>The Holy Bible 20 (Remastered)</album>
  <album>The Ultra Vivid Lament (Deluxe Edition)</album>
  <album>The Ultra Vivid Lament (Deluxe Edition)</album>
  <album>This Is My Truth Tell Me Yours</album>
  <album>This Is My Truth Tell Me Yours</album>
  </albums>
</artist>