<?xml version="1.0" encoding="UTF-8"?>
<album>
  <genres>
    <genre>pop</genre>
    <genre>female-vocalists</genre>
    <genre>alternative</genre>
    <genre>chillout</genre>
    <genre>trance</genre>
    <genre>lounge</genre>
    <genre>electronic</genre>
    <genre>christmas</genre>
    <genre>90s</genre>
    <genre>female-vocalist</genre>
    <genre>soundtrack</genre>
    <genre>acoustic</genre>
    <genre>cover</genre>
    <genre>dance</genre>
    <genre>rock</genre>
    <genre>pop-rock</genre>
    <genre>piano</genre>
    <genre>80s</genre>
  </genres>
</album>