<?xml version="1.0" encoding="UTF-8"?>
<artist>
  <name>The Beau Brummels</name>
  <albums>
    <album>'60s Garage Nuggets</album>
    <album>100 Classics - Malt Shop Memories</album>
    <album>19 Of Their Best</album>
    <album>20th Century Rocks: 60's Rock Bands - Wild Thing</album>
    <album>25 Classics - Malt Shop Memories Vol. 3</album>
    <album>60's Party Hits - Wilson Pickett, Billie Davis & Friends</album>
    <album>60's Rock Bands - Wild Thing</album>
    <album>60s Beat Groups</album>
    <album>60s Pop Classics-Vol.2</album>
    <album>All-Time Greatest Hits</album>
    <album>American Diner Classics</album>
    <album>Beau Brummels '66 (Mono)</album>
    <album>Best 60s Rock</album>
    <album>Bradley's Barn</album>
    <album>Early Morning Rain - Folk Rock Classics</album>
    <album>Far out Psychedelic Pop</album>
    <album>From The Vaults</album>
    <album>Introducing the Beau Brummels</album>
    <album>Introducing The Beau Brummels (Digitally Remastered)</album>
    <album>Just a Little - Best of The Beau Brummels</album>
    <album>Laugh Laugh</album>
    <album>Laugh Laugh & Other Favorites (Digitally Remastered)</album>
    <album>Laugh, Laugh</album>
    <album>Magic Hollow</album>
    <album>Put the Top Down - Summer 60's</album>
    <album>Sad Little Girl</album>
    <album>San Francisco Rock</album>
    <album>San Francisco Roots (Digitally Remastered)</album>
    <album>San Francisco Sound: The Beau Brummels</album>
    <album>Still In Love With You Baby</album>
    <album>The '60s Hits: Soundtrack Rarities Edition</album>
    <album>The Beau Brummels, Vol. 2</album>
    <album>The Beau Brummels: Volume 2</album>
    <album>The Best of Sixties Pop, Rock and R&B</album>
    <album>The Best Of The Beau Brummels (Remastered)</album>
    <album>The Original Hits of the Beau Brummels</album>
    <album>The Soul of 1960s Rock</album>
    <album>Triangle</album>
    <album>Turn Around: The Complete Recordings 1964-1970</album>
    <album>Ultimate 60's Party Hits - Wilson Pickett, Billie Davis & Friends</album>
  </albums>
</artist>