<?xml version="1.0" encoding="UTF-8"?>
<artist>
  <name>The Chords</name>
  <albums>
    <album>Atlantic Top 60: R&B Grooves</album>
    <album>Doo Wop Greatest Hits</album>
    <album>Early Years Of Rock 'N' Roll Volume 2</album>
    <album>In Mint Condition</album>
    <album>It Was Twenty Years Ago Today</album>
    <album>Life Could Be a Dream: The Sh-Boom Sound of The Chords</album>
    <album>Malt Shop Doo Wop</album>
    <album>Presenting The Chords</album>
    <album>Red Hot Doo Wop, Vol. 1</album>
    <album>Sh-Boom & the Doo-Wop Hits</album>
    <album>So Far Away</album>
    <album>The History Of Rhythm & Blues Vol.2: The Golden Years 1953-1955</album>
  </albums>
</artist>