<?xml version="1.0" encoding="UTF-8"?>
<artist>
  <name>Roadrunner United</name>
  <albums>
    <album>(Sic) [Live at the Nokia Theatre, New York, NY, 12-15-2005]</album>
    <album>The All Star Sessions</album>
    <album>The All-Star Sessions (Atmos Mix)</album>
    <album>The Concert (Live at the Nokia Theatre, New York, NY, 12-15-2005)</album>
    <album>The Concert (Live at the Nokia Theatre, New York, NY, 12/15/2005)</album>
    <album>The Dagger (Live at the Nokia Theatre, New York, NY, 12-15-2005)</album>
    <album>The End (Live at the Nokia Theatre, New York, NY, 12-15-2005)</album>
    <album>The Rich Man (Live at the Nokia Theatre, New York, NY, 12-15-2005)</album>
  </albums>
</artist>