<?xml version="1.0" encoding="UTF-8"?>
<artist>
  <name>DLRM</name>
  <albums>
    <album>Bogáncs</album>
    <album>Can You Hear Me Calling-</album>
    <album>Cheeky Pig</album>
    <album>Chew Me</album>
    <album>Dance with Me</album>
    <album>Dear Danube</album>
    <album>Eukaliptusz</album>
    <album>Gypsindie</album>
    <album>HAINAL</album>
    <album>Ladybird & Candylight</album>
    <album>Lila</album>
    <album>Should</album>
    <album>Spellbound</album>
    <album>Suckerpunch</album>
    <album>Turquoise Rendez Vous</album>
    <album>Watching Me EP</album>
  </albums>
</artist>