<?xml version="1.0" encoding="UTF-8"?>
<artist>
  <name>William Parker</name>
  <albums>
    <album>At Somewhere There</album>
    <album>Bakunawa</album>
    <album>Bob’s Pink Cadillac</album>
    <album>Book of Sound</album>
    <album>Broken Unbroken</album>
    <album>Cereal Music</album>
    <album>Cherry Box</album>
    <album>Corn Meal Dance</album>
    <album>Crumbling In The Shadows Is Fraulein Miller's Stale Cake</album>
    <album>Double Sunrise Over Neptune</album>
    <album>Flower In a Stained-Glass Window & The Blinking of The Ear</album>
    <album>For Those Who Are, Still</album>
    <album>Great Spirit</album>
    <album>Heart Trio</album>
    <album>Heptagon</album>
    <album>I Plan To Stay A Believer- The Inside Songs of Curtis Mayfield</album>
    <album>In Order To Survive</album>
    <album>Ineffable Joy</album>
    <album>Lake of Light- Compositions for Aquasonics</album>
    <album>Long Hidden- The Olmec Series</album>
    <album>Mayan Space Station</album>
    <album>New World Pygmies</album>
    <album>Old Song Resung- William Parker Sings Ives, Griffes, Farwell, and Cadman</album>
    <album>Painter's Spring</album>
    <album>Painters Winter</album>
    <album>Piercing The Veil</album>
    <album>Raining On The Moon</album>
    <album>Seraphic Light</album>
    <album>Songs of Brahms and Copland</album>
    <album>Sparks</album>
    <album>Summer Snow</album>
    <album>Testimony</album>
    <album>The All-Star Game</album>
    <album>The Listeners</album>
    <album>Thinking Unthinking</album>
    <album>Through Acceptance Of The Mystery Peace</album>
    <album>Titan</album>
    <album>Trencadis- a selection from Migration of Silence Into and Out of The Tone World</album>
    <album>Two Days In April</album>
    <album>Uncle Joe's Spirit House</album>
    <album>Universal Tonality</album>
    <album>Village Mothership</album>
    <album>Voices Fall From The Sky</album>
    <album>Washed Away (Live at the Sunside)</album>
    <album>Wood Flute Songs- Anthology - Live 2006-2012</album>
  </albums>
</artist>