<?xml version="1.0" encoding="UTF-8"?>
<artist>
  <name>red hot chili peppers</name>
  <albums>
    <album>Blood Sugar Sex Magik</album>
  <album>Blood Sugar Sex Magik (Deluxe Edition)</album>
  <album>By the Way</album>
  <album>By the Way (Deluxe Edition)</album>
  <album>Californication</album>
  <album>Californication (Deluxe Edition)</album>
  <album>Freaky Styley</album>
  <album>Greatest Hits</album>
  <album>I'm with You</album>
  <album>Mother's Milk</album>
  <album>Mother's Milk (Remastered)</album>
  <album>One Hot Minute</album>
  <album>Red Hot Chili Peppers</album>
  <album>Return of the Dream Canteen</album>
  <album>Stadium Arcadium</album>
  <album>The Getaway</album>
  <album>The Studio Album Collection 1991 - 2011</album>
  <album>The Uplift Mofo Party Plan</album>
  <album>Unlimited Love</album>
  </albums>
</artist>