<?xml version="1.0" encoding="UTF-8"?>
<artist>
  <name>Shine</name>
  <albums>
    <album>ALWAYS ABOUT U (feat. Grimm Lynn) [SINGLE VERSION]</album>
    <album>California Sunshine</album>
    <album>Invincible</album>
    <album>Judas and Mary</album>
    <album>Kuszą Was (Radio Edit)</album>
    <album>more pLUSH</album>
    <album>PRIVATE PARTY</album>
    <album>Radiostar</album>
    <album>Sounds From The Afterlife - Concept Album For "Messorem"</album>
    <album>The Common Station</album>
  </albums>
</artist>