<?xml version="1.0" encoding="UTF-8"?>
<artist>
  <name>Jungle Brothers</name>
  <albums>
    <album>Because I Got It Like That</album>
    <album>Dance Nation</album>
    <album>Dôme Ibiza - The Chill-Out Session, Vol. 2</album>
    <album>Done By The Forces Of Nature</album>
    <album>Done By The Forces Of Nature (Deluxe Edition)</album>
    <album>I'll House You</album>
    <album>I'll House You '98</album>
    <album>Jimbrowski</album>
    <album>Keep it Jungle</album>
    <album>On The Floor At The Boutique</album>
    <album>Red Hot + Blue: A Tribute to Cole Porter</album>
    <album>Straight out the Jungle</album>
    <album>Straight Out The Jungle</album>
    <album>Straight out the Jungle: The Instrumental Show</album>
  </albums>
</artist>