<?xml version="1.0" encoding="UTF-8"?>
<artist>
  <name>Stretch & Vern</name>
  <albums>
    <album>Armada Music Year Mix 2024</album>
    <album>Get Up! Go Insane! (Remastered & Remixed 2019)</album>
    <album>I'm Alive</album>
    <album>I'm Alive (Friend Within Remix)</album>
    <album>I'm Alive (Illyus & Barrientos Refix Edit)</album>
    <album>I'm Alive (Illyus & Barrientos Refix)</album>
    <album>I'm Alive (Prins Thomas Diskomix)</album>
    <album>I'm Alive (Remastered & Remixed 2019)</album>
  </albums>
</artist>