<?xml version="1.0" encoding="UTF-8"?>
<artist>
  <name>And One</name>
  <albums>
    <album>Anguish</album>
    <album>Bodypop (Special Edition)</album>
    <album>Computerstar</album>
    <album>Flop!</album>
    <album>Frontfeuer</album>
    <album>I.S.T.</album>
    <album>Live (Live Steffi)</album>
    <album>Magnet</album>
    <album>Military Fashion Show</album>
    <album>S.T.O.P.</album>
    <album>So klingt Liebe (E)</album>
    <album>So Klingt Liebe (S)</album>
    <album>So Klingt Liebe (X)</album>
    <album>Spot</album>
    <album>Tanzomat</album>
    <album>Zerstörer</album>
  </albums>
</artist>