<?xml version="1.0" encoding="UTF-8"?>
<artist>
  <name>Ruthie Foster</name>
  <albums>
    <album>Crossover</album>
    <album>Healing Time</album>
    <album>Joy Comes Back</album>
    <album>Keep It Burning</album>
    <album>Let It Burn</album>
    <album>Live at the Paramount</album>
    <album>Mileage</album>
    <album>Promise of a Brand New Day</album>
    <album>Ruthie Foster Live at Antone's</album>
    <album>The Phenomenal Ruthie Foster</album>
    <album>The Truth According to Ruthie Foster</album>
  </albums>
</artist>