<?xml version="1.0" encoding="UTF-8"?>
<artist>
  <name>Jack White</name>
  <albums>
    <album>Another Day, Another Time: Celebrating the Music of 'Inside Llewyn Davis'</album>
    <album>As I Am (Expanded Edition)</album>
    <album>Blunderbuss</album>
    <album>Boarding House Reach</album>
    <album>Cold Mountain (Music From the Miramax Motion Picture)</album>
    <album>Connected by Love</album>
    <album>Connected by Love (Radio Edit)</album>
    <album>Entering Heaven Alive</album>
    <album>Fear Of The Dawn</album>
    <album>Freedom At 21</album>
    <album>I'm Shakin'</album>
    <album>Jack White Acoustic Recordings 1998 - 2016</album>
    <album>Lazaretto</album>
    <album>Love Interruption</album>
    <album>No Name</album>
    <album>No Name Live</album>
    <album>Quantum of Solace: Original Motion Picture Soundtrack</album>
    <album>Quantum Of Solace: Original Motion Picture Soundtrack</album>
    <album>Sixteen Saltines</album>
    <album>That Black Bat Licorice - Single</album>
    <album>Would You Fight For My Love?</album>
    <album>You Got Me Searching</album>
  </albums>
</artist>