<?xml version="1.0" encoding="UTF-8"?>
<artist>
  <name>Max Corbacho</name>
  <albums>
    <album>A Connection to the Wonder</album>
    <album>A Connection to the Wonder, Pt. 1</album>
    <album>A Connection to the Wonder, Pt. 2</album>
    <album>Ars Lucis</album>
    <album>Bora Scura Reimagined</album>
    <album>BreathStream</album>
    <album>Circle of Grace</album>
    <album>Dreaming Spaces</album>
    <album>Equinox</album>
    <album>Far Beyond the Immobile Point</album>
    <album>Fragment of a Dream (73 Min Extended Version)</album>
    <album>Horizon Matrix</album>
    <album>Indalo</album>
    <album>Lost Links II - The Complete Collection</album>
    <album>Moontribe</album>
    <album>Nocturnes</album>
    <album>Nocturnes II</album>
    <album>Nocturnes III</album>
    <album>Source of Present</album>
    <album>The Delicate Essence of Solitude</album>
    <album>The Talisman</album>
    <album>The Unfolding Dawn</album>
  </albums>
</artist>