<?xml version="1.0" encoding="UTF-8"?>
<artist>
  <name>Carl Cox</name>
  <albums>
    <album>All Roads Lead to the Dancefloor</album>
    <album>Amsterdam 2017 (Mixed)</album>
    <album>Beat the Track</album>
    <album>Chemistry</album>
    <album>Cr2 Introducing (Jewel Kid Deluxe Edition)</album>
    <album>Cr2 Presents: Live & Direct #6 By Skiy (DJ Mix)</album>
    <album>Dr. Funk (Riva Starr Remixes)</album>
    <album>Electronic Generations</album>
    <album>Elrow, Vol. 2 (DJ Mix)</album>
    <album>I Want You (Forever)</album>
    <album>I Want You (Forever) (Josh Butler Remix - Shorter Edit)</album>
    <album>I Want You (Forever) (Josh Butler Remix)</album>
    <album>Ibiza 2019 (DJ Mix)</album>
    <album>Ibiza Opening Party 2019 - After Hours (DJ Mix)</album>
    <album>Ice (20 Years Systematic)</album>
    <album>Inferno</album>
    <album>Intec50 Ep</album>
    <album>International Techno Vol 1</album>
    <album>International Techno Vol 2</album>
    <album>Live & Direct #4 (DJ Mix)</album>
    <album>Live & Direct 09 (DJ Mix)</album>
    <album>Morroccan Chant Number 2</album>
    <album>Nexus</album>
    <album>Our Time Will Come (Chase & Status Remix)</album>
    <album>Privilege Ibiza 2017</album>
    <album>Pure Intec 2 Mixed by Carl Cox & Jon Rundell</album>
    <album>Second Sign</album>
    <album>See the Sun Rising</album>
    <album>See You Next Tuesday</album>
    <album>Space Ibiza 2016 (DJ Mix)</album>
    <album>Speed Trials On Acid (feat. Dan Diamond)</album>
    <album>Speed Trials On Acid (feat. Dan Diamond) (LF SYSTEM Remix)</album>
    <album>Speed Trials On Acid (feat. Dan Diamond) (Riton Remix)</album>
    <album>Techno, Vol. 1</album>
    <album>The Latin Theme (feat. Savanah Blount)</album>
    <album>The Remixes, Pt. 1</album>
    <album>Time for House Music</album>
    <album>Welcome to My World</album>
  </albums>
</artist>