<?xml version="1.0" encoding="UTF-8"?>
<artist>
  <name>Santa Esmeralda</name>
  <albums>
    <album>Another Cha Cha - Cha Cha Suite</album>
    <album>Don’t Let Me Be Misunderstood (Granite & Sugarman Remixes)</album>
    <album>Hits Anthology</album>
    <album>SANTA ESMERALDA (Greatest Hits Ever Remastered)</album>
    <album>Santa Esmeralda (Greatest Hits)</album>
    <album>Santa Esmeralda Selected Hits</album>
    <album>The House of the Rising Sun - Quasimodo Suite</album>
  </albums>
</artist>