<?xml version="1.0" encoding="UTF-8"?>
<artist>
  <name>Fiordaliso</name>
  <albums>
    <album>Come Si Fà</album>
    <album>E adesso voglio la luna (I grandi successi)</album>
    <album>Fiordaliso live (Live)</album>
    <album>FriKandò</album>
    <album>Il mare più grande che c'è (I love you man - acoustic 2019)</album>
    <album>Il mare più grande che c'è e... altre storie</album>
    <album>Il meglio vol.3</album>
    <album>Italian Best Hits</album>
    <album>Italian Classics Unforgettable Songs</album>
    <album>Italian Hits</album>
    <album>Italian Hits Unforgettable Songs</album>
    <album>Made In Italy</album>
    <album>Non Voglio Mica La Luna</album>
    <album>Sponsorizzata</album>
  </albums>
</artist>