<?xml version="1.0" encoding="UTF-8"?>
<artist>
  <name>Dooley Wilson</name>
  <albums>
    <album>As Time Goes By</album>
    <album>BD Music Presents BD Ciné</album>
    <album>BD Music Presents Film Noir</album>
    <album>BD Music Presents Woody Allen's Movies, Vol. 1</album>
    <album>Casablanca (Original Motion Picture Soundtrack)</album>
    <album>Film Ringtones, Vol. 1</album>
    <album>Hollywood 1927-1950 - Le Plus Grand Thèmes Chantés Du Cinéma</album>
    <album>If I Were A Rich Man</album>
    <album>Quiet Village</album>
    <album>Singing in the Movies, Vol. 2</album>
    <album>Songs of the 1940s Before and After the Wartime</album>
    <album>Straighten Up & Fly Right: Hollywood Hits 1940 - 1955</album>
    <album>The Great American Songbook - 50 Hits!</album>
    <album>The Hits Collection 1943</album>
    <album>The Very Best of Jazz - 50 Unforgettable Tracks (Remastered)</album>
    <album>The Very Best Of The 40s - Volume 2</album>
    <album>There'll Always Be An England - Great War Songs Vol 3</album>
    <album>Unforgettable - The Memory Lingers On Volume 3</album>
  </albums>
</artist>