<?xml version="1.0" encoding="UTF-8"?>
<artist>
  <name>Artie Shaw</name>
  <albums>
    <album>"On the Air" 1939-1940</album>
    <album>"Serie All Stars Music" Nº5 Exclusive Remastered From Original Vinyl First Edition (Vintage LPs)</album>
    <album>100 Best Dance Orchestras</album>
    <album>100 Famous Historical Jazz Songs (Essentials Louis Armstrong)</album>
    <album>100 Jazz Classics</album>
    <album>100 Mejores Grandes Orquestas</album>
    <album>100 Vintage Jazz Favorites</album>
    <album>150 Jazz Classics</album>
    <album>1936 To 1940 Broadcasts</album>
    <album>1937 - 1939</album>
    <album>1938-39 Old Gold Shows</album>
    <album>20 Songs from Shooter Games</album>
    <album>22 Original Big Band Hits</album>
    <album>25 Of His Best</album>
    <album>30 Greatest Hits</album>
    <album>30 Hits of Artie Shaw</album>
    <album>40 Hits of Artie Shaw</album>
    <album>40's Dance Party</album>
    <album>49 Essential Artie Shaw Classics, Vol. 4</album>
    <album>50 Great Big Swing Hits!</album>
    <album>50 Hits of Artie Shaw</album>
    <album>50 Shades of Jazz, Vol. 66</album>
    <album>60 Classic Recordings to Celebrate International Jazz Day</album>
    <album>60 Years Of Music America Loves Best, Vol. 2</album>
    <album>99 Hits : Artie Shaw</album>
    <album>A Man And His Dream</album>
    <album>A Pop Artist Concert</album>
    <album>Aaah! - Artie Shaw, Vol. 1</album>
    <album>Aaah! - Artie Shaw, Vol. 2</album>
    <album>All Artie - 50 Tunes</album>
    <album>All the Things You Are</album>
    <album>American Hits: Big Band</album>
    <album>American Horror Songs</album>
    <album>An Hour With Artie Shaw</album>
    <album>Art Attack - The Seminal Artie Shaw</album>
    <album>Artie Selection</album>
    <album>Artie Shaw</album>
    <album>Artie Shaw - 50 Hot Hits</album>
    <album>Artie Shaw - Broadway Session (MP3 Album)</album>
    <album>Artie Shaw - Gold Collection</album>
    <album>Artie Shaw - The Best</album>
    <album>Artie Shaw - The Gold Clarinet, Vol. 1</album>
    <album>Artie Shaw - The Gold Clarinet, Vol. 2</album>
    <album>Artie Shaw - The Gold Clarinet, Vol. 3</album>
    <album>Artie Shaw - The Gold Clarinet, Vol. 4</album>
    <album>Artie Shaw : Swing & Big Band Music</album>
    <album>Artie Shaw & His Orchestra</album>
    <album>Artie Shaw & His Orchestra, Vol.1, 1938</album>
    <album>Artie Shaw & His Orchestra, Vol.2, 1938</album>
    <album>Artie Shaw 1945 Spotlight Bands Broadcasts</album>
    <album>Artie Shaw And His New Music , 1937 (Hq Remastered)</album>
    <album>Artie Shaw and his Orchestra - 75 Favorites by Artie Shaw (MP3 Compilation)</album>
    <album>Artie Shaw and his Orchestra - Big Bands</album>
    <album>Artie Shaw And His Orchestra 1938</album>
    <album>Artie Shaw and His Orchestra Selected Favorites Volume 1</album>
    <album>Artie Shaw and His Orchestra Selected Favorites Volume 2</album>
    <album>Artie Shaw and His Orchestra Selected Favorites, Vol. 2</album>
    <album>Artie Shaw And His Orchestra Selected Hits Vol. 1</album>
    <album>Artie Shaw And His Orchestra Selected Hits Vol. 2</album>
    <album>Artie Shaw And His Orchestra Selected Hits Vol. 3</album>
    <album>Artie Shaw And His Orchestra Vol. 1 1938</album>
    <album>Artie Shaw Diamond</album>
    <album>Artie Shaw Hour</album>
    <album>Artie Shaw Selected Favorites Volume 2</album>
    <album>Artie Shaw Selected Favorites, Vol. 2</album>
    <album>Artie Shaw Selected Favorites, Vol. 3</album>
    <album>Artie Shaw Selected Hits</album>
    <album>Artie Shaw Thesaurus</album>
    <album>Artie Shaw Vol. 10</album>
    <album>Artie Shaw Vol. 5</album>
    <album>Artie Shaw: 1937 - 1939</album>
    <album>Artie Shaw: Gramercy 5, Vol. 1</album>
    <album>Artie Shaw: The Complete Jazz Heritage Society Recordings</album>
    <album>Artie's Art</album>
    <album>At the Hollywood Palladium (Live)</album>
    <album>Back Bay Shuffle</album>
    <album>Backline, Vol. 444</album>
    <album>Begin the Beguine</album>
    <album>Begin The Beguine</album>
    <album>Best Of The V Discs</album>
    <album>Beyond Patina Jazz Masters: Artie Shaw</album>
    <album>Big Band Classics, Volume 5</album>
    <album>Big Band Definitive Collection</album>
    <album>Big Band Music Club: Too Marvelous for Words, Vol. 4</album>
    <album>Big Band Music Deluxe: Dance Hall Days, Vol. 4</album>
    <album>Big Band Music Deluxe: The Village Sessions, Vol. 3</album>
    <album>Big Band Songs</album>
    <album>Big Band Superstars</album>
    <album>Blue Interlude</album>
    <album>Blue Room</album>
    <album>Blue Skies</album>
    <album>Body & Soul (Featuring jazz musicians from all over the world!)</album>
    <album>Both Feet in the Groove</album>
    <album>Bottle Rocket Short Film Soundtrack</album>
    <album>Café Rouge</album>
    <album>Carnival</album>
    <album>Clarinet Master</album>
    <album>Collection of the Best Big Bands - Artie Shaw, Vol. 1 (Remastered)</album>
    <album>Complete Jazz Series 1937</album>
    <album>Complete Jazz Series 1938</album>
    <album>Complete Jazz Series 1939 Vol. 2</album>
    <album>Complete Jazz Series 1945 - 1946</album>
    <album>Concerto for Clarinet</album>
    <album>Concerto For Clarinet</album>
    <album>Cool Daddy Experiments with Be-Bop</album>
    <album>Crooners and Sirens Vol. 12</album>
    <album>Dance To Artie Shaw</album>
    <album>Dancing in the Dark</album>
    <album>Definitive Artie Shaw, Vol. 5</album>
    <album>Definitive Artie Shaw, Vol. 6</album>
    <album>Dynamic Jazz: 50 Essential Tracks</album>
    <album>Electro Swing Fever 2015 (The Best Electronic, Retro, Jazzy Lounge Playlist)</album>
    <album>Essential Classics, Vol. 306: Artie Shaw</album>
    <album>Evensong</album>
    <album>Evergreens of Big Bands, Vol. 3</album>
    <album>For You, For Me, Forevermore</album>
    <album>Free For All</album>
    <album>Frenesi</album>
    <album>Get out of Town</album>
    <album>Golden Artists Of The USA, Vol. 6</album>
    <album>Goodman & Shaw</album>
    <album>Great Hits of Artie Shaw</album>
    <album>Great Instumental Favorites</album>
    <album>Great Jazz Compositions</album>
    <album>Greatest Big Band Classics</album>
    <album>Hit Parade Platinum Collection Artie Shaw Begin The Beguine</album>
    <album>Hop, Skip And Jump (Original)</album>
    <album>If I Had You</album>
    <album>In The Blue Room In The Cafe Rouge</album>
    <album>In the Still of the Night</album>
    <album>In The Still Of The Night</album>
    <album>It Had To Be You</album>
    <album>Jazz Giants: Artie Shaw</album>
    <album>Jazz Golden Collection</album>
    <album>Jazz Nostalgia</album>
    <album>Jazz Selection (Doxy Collection)</album>
    <album>Jumpin' Jive!</album>
    <album>Jungle Drums</album>
    <album>Just Jazz Presents, Artie Shaw</album>
    <album>Just Lounging Around - Part 2</album>
    <album>L.A. Noir - Mob Hits</album>
    <album>Ladies & Gentlemen It's Artie Shaw</album>
    <album>Last Recordings, Volume 1</album>
    <album>Le disque d'or de la clarinette</album>
    <album>Legends Of Jazz: Artie Shaw - Stardust</album>
    <album>Let's Do the Charleston</album>
    <album>Let's Go For Shaw!</album>
    <album>Little Jazz</album>
    <album>Little Jazz, Vol. 3</album>
    <album>Little Jazz, Vol. 6</album>
    <album>Live At The Blue Room</album>
    <album>Live At The Cafe Rouge</album>
    <album>Live From New York's Café Rouge</album>
    <album>Masters Of Swing - Artie Shaw</album>
    <album>Memories of the Big Band Era - Artie Shaw</album>
    <album>Memories Of The Big Band Era - Artie Shaw</album>
    <album>Moonglow</album>
    <album>My Blue Heaven</album>
    <album>Night and Day</album>
    <album>Nightmare</album>
    <album>No More Tears</album>
    <album>No Regrets</album>
    <album>Non-Stop Flight</album>
    <album>Nostalgic Memories-The Very Best of Artie Shaw-Vol. 83</album>
    <album>Old Gold "Melody & Madness" Shows</album>
    <album>One Night Stand</album>
    <album>Piano Man (Greatest 1930s Swing Records)</album>
    <album>Rose Room</album>
    <album>Saga Jazz: Big Bands - Live !!!</album>
    <album>Selections from "The Man Who Fell to Earth" (Original Motion Picture Soundtrack)</album>
    <album>September Song</album>
    <album>Serenade to a Savage</album>
    <album>Shaw, Artie: Begin the Beguine (1936-1939)</album>
    <album>Shaw, Artie: Concertos for Clarinet (1937-1940)</album>
    <album>Solid Gold Artie Shaw</album>
    <album>Somebody Nobody Love: The Artie Shaw Collection, Vol. 5</album>
    <album>Somebody Nobody Love: The Artie Shaw Collection, Vol. 7</album>
    <album>Sound of the Movies Vol. 11</album>
    <album>Spotlight Bands Broadcast Volume One (Live San Diego 1945)</album>
    <album>Stardust</album>
    <album>Stars, Vol. 11</album>
    <album>Sweet and Simple</album>
    <album>Swing Sessions</album>
    <album>Swing Time For Dancing Vol. 8</album>
    <album>Swing Time For Dancing Vol. 9</album>
    <album>Swing! Big Band Sounds</album>
    <album>Swinging Time, Vol. 12</album>
    <album>Temptation (Remastered)</album>
    <album>The Art Of Swing</album>
    <album>The Artistry of Artie Shaw and His Bop Band, 1949</album>
    <album>The Bandleader</album>
    <album>The Best of</album>
    <album>The Best of Artie Shaw</album>
    <album>The Big Band Collection, Vol. 4</album>
    <album>The Chant</album>
    <album>The Complete 1945 Christmas Radio Show</album>
    <album>The Complete Rhythm Makers Sessions 1937 - 1938 - Volume 1</album>
    <album>The Complete Rhythm Makers Sessions 1937 - 1938 - Volume 2</album>
    <album>The Complete Rhythm Makers Sessions 1937 - 1938 - Volume 3</album>
    <album>The Complete Thesaurus Transcriptions 1949</album>
    <album>The Discovery of Jazz</album>
    <album>The Early Artie Shaw, Vol. 3</album>
    <album>The Encyclopedia Jazz</album>
    <album>The Essential Series Remastered: Artie Shaw And His Orchestra Vol. 2 1938-39 (Remastered 2023)</album>
    <album>The Essential Series Remastered: Artie Shaw And His Orchestra Vol. 3 1939 (Remastered 2025)</album>
    <album>The Giants of Swing, Artie Shaw Vol. 1</album>
    <album>The Good Ol' Boys Club Solos… Duos… Trios… And Fours!</album>
    <album>The Great Artie Shaw</album>
    <album>The Great Artie Shaw Collection, Vol. 6</album>
    <album>The Great Artie Shaw Collection, Vol. 7</album>
    <album>The Great Artie Shaw Collection, Vol. 8</album>
    <album>The Great Jazz Collection: Vol. 2</album>
    <album>The Just Artie Shaw, Vol.2</album>
    <album>The Last Artie Shaw Orchestra</album>
    <album>The Latin Summer All-time Classics Collection, Vol. 2</album>
    <album>The Legendary Music of Duke Ellington, Teddy Wilson, Sonny Rollins, Duke Ellington and Other Hits, Vol. 1 (140 Songs)</album>
    <album>The look of Love (Featuring jazz musicians from all over the world!)</album>
    <album>The Million Sellers Vol.2</album>
    <album>The Original Big Band</album>
    <album>The Standards</album>
    <album>The Story Of Jazz</album>
    <album>The Swing Band Project: In Person - Artie Shaw</album>
    <album>The Swing Era</album>
    <album>The Ultimate Jazz Store, Vol. 11</album>
    <album>The Very Best of Artie Shaw</album>
    <album>The Very Best of Artie Shaw, Vol. 10</album>
    <album>The Very Best of Artie Shaw, Vol. 5</album>
    <album>Themes Of The Great Bands</album>
    <album>These Foolish Things: The Decca Years</album>
    <album>This Is Pomance, Vol. 2</album>
    <album>This Is Pomance, Vol. 4</album>
    <album>This is Romance Vol 2</album>
    <album>This is Romance Vol 4</album>
    <album>Three of a Kind: Tommy Dorsey, Artie Shaw, Benny Goodman</album>
    <album>Traffic Jam</album>
    <album>Treasures Big Band Classics : Artie Shaw Vol.1</album>
    <album>Two of a Kind: Artie Shaw & Les Brown</album>
    <album>Two of a Kind: Fats Waller & Artie Shaw</album>
    <album>Two of a Kind: Lionel Hampton & Artie Shaw</album>
    <album>Two of a Kind: Ted Heath & Artie Shaw, Part 1</album>
    <album>Underneath the Spanish Stars</album>
    <album>Vintage Vinyl Collection - Acker Bilk and Artie Shaw (100 Remastered Clarinet Tracks)</album>
    <album>Wonders of the Wartime: Artie Shaw</album>
    <album>Yesterdays</album>
    <album>懐かしい名曲</album>
  </albums>
</artist>