<?xml version="1.0" encoding="UTF-8"?>
<artist>
  <name>N.E.R.D</name>
  <albums>
    <album>Fly Or Die</album>
    <album>Hot-n-Fun The Remixes</album>
    <album>Hypnotize U The Remixes</album>
    <album>In Search Of...</album>
    <album>Lapdance</album>
    <album>Lemon</album>
    <album>Lemon (Edit)</album>
    <album>Maybe</album>
    <album>NO ONE EVER REALLY DIES</album>
    <album>Nothing</album>
    <album>Rock Star</album>
    <album>Seeing Sounds</album>
    <album>Sessions@AOL EP</album>
    <album>She Wants To Move</album>
    <album>The Best Of</album>
  </albums>
</artist>