<?xml version="1.0" encoding="UTF-8"?>
<artist>
  <name>Groove Armada</name>
  <albums>
    <album>Black Light</album>
  <album>Black Light</album>
  <album>Edge of the Horizon</album>
  <album>Edge of the Horizon</album>
  <album>GA10</album>
  <album>GA10</album>
  <album>Goodbye Country (Hello Nightclub)</album>
  <album>Goodbye Country (Hello Nightclub)</album>
  <album>Groove Armada Greatest Hits</album>
  <album>Groove Armada Greatest Hits</album>
  <album>Last Night in Brixton</album>
  <album>Last Night in Brixton</album>
  <album>Late Night Tales Presents Automatic Soul (Selected and Mixed by Groove Armada's Tom Findlay)</album>
  <album>Late Night Tales Presents Automatic Soul (Selected and Mixed by Groove Armada's Tom Findlay)</album>
  <album>Little Black Book</album>
  <album>Little Black Book</album>
  <album>Lovebox</album>
  <album>Lovebox</album>
  <album>Northern Star 15th Anniversary</album>
  <album>Northern Star 15th Anniversary</album>
  <album>Soundboy Rock</album>
  <album>Soundboy Rock</album>
  <album>Sounds Good In The Nude (Selected and Mixed by Tim Love Lee and Groove Armada's Tom Findlay)</album>
  <album>Sounds Good In The Nude (Selected and Mixed by Tim Love Lee and Groove Armada's Tom Findlay)</album>
  <album>The Remixes</album>
  <album>The Remixes</album>
  <album>Vertigo</album>
  <album>Vertigo</album>
  <album>White Light</album>
  <album>White Light</album>
  </albums>
</artist>