<?xml version="1.0" encoding="UTF-8"?>
<artist>
  <name>Najee</name>
  <albums>
    <album>Blue Note Plays Stevie Wonder</album>
    <album>Center of the Heart</album>
    <album>Classic Masters</album>
    <album>Day By Day</album>
    <album>Dr. Dolittle</album>
    <album>Embrace</album>
    <album>Forever, For Always, For Luther, Vol. 2</album>
    <album>Just An Illusion</album>
    <album>Morning Tenderness</album>
    <album>Najee's Theme</album>
    <album>Poetry In Motion</album>
    <album>Salvador</album>
    <album>Savoir Faire</album>
    <album>Sax Me</album>
    <album>Sensuous Smooth Jazz For Lovers</album>
    <album>Songs From The Key Of Life: A Tribute To Stevie Wonder</album>
    <album>Summer In The SHDWs</album>
    <album>Summer in The SHDWs Extended</album>
    <album>The Best Of Najee</album>
    <album>The Smooth Side Of Soul</album>
    <album>TOKYO BLUE</album>
    <album>Under the Moon over the Sky</album>
    <album>You, Me And Forever</album>
  </albums>
</artist>