<?xml version="1.0" encoding="UTF-8"?>
<artist>
  <name>Dean Martin</name>
  <albums>
    <album>"Serie All Stars Music" Nº10 Exclusive Remastered From Original Vinyl First Edition (Vintage LPs)</album>
    <album>(Remember Me) I'm the One That Loves You</album>
    <album>100 Après Ski Party Schlager Hits 2015 (Original Hits für die Apres Ski Fete)</album>
    <album>100 Christmas Classics</album>
    <album>100 Essential Crooner Hits</album>
    <album>100 Golden Greats (The Rat Pack) [Remastered]</album>
    <album>100 Party Schlager der 50er & 60er</album>
    <album>100 tubes américains (1945-1960)</album>
    <album>101 Hits - Dean Martin</album>
    <album>11 Original Albums Dean Martin, Vol.4</album>
    <album>20 Fabulous No. 1's of the 50's (Digitally Remastered)</album>
    <album>25 Love Songs</album>
    <album>80 Childrens Christmas Songs</album>
    <album>85 Famous Dean Martin's Masterpieces (Original Recordings Digitally Remastered)</album>
    <album>A Portrait of Dean Martin</album>
    <album>A Winter Romance</album>
    <album>Absolutely: Christmas Classics</album>
    <album>All I Do Is Dream of You</album>
    <album>As I Remember Them 1953</album>
    <album>At The Movies</album>
    <album>Baby It's Cold Outside (Cool Yule)</album>
    <album>Baby, It's Cold Outside</album>
    <album>Baby, It's Cold Outside, Vol. 1</album>
    <album>Baby, It's Cold Outside, Vol. 2</album>
    <album>Baby, It's Cold Outside, Vol. 3</album>
    <album>Baby, It's Cold Outside, Vol. 4</album>
    <album>BD Music Presents Dean Martin</album>
    <album>Beautiful Christmas (The Best Carols Ever)</album>
    <album>Bella Bimba</album>
    <album>Best DEAN MARTIN Early Movie Themes & Songs, Vol. 2</album>
    <album>Best HOWARD HAWKS Movie Themes</album>
    <album>Best Of</album>
    <album>Best Of…</album>
    <album>Bianco Natale (Canzoncine Natalizie)</album>
    <album>Bing Crosby, Dean Martin and Frank Sinatra Christmas Classics</album>
    <album>Blockbuster Movie Hits</album>
    <album>Blue Collection: Dean Martin</album>
    <album>Buona Sera</album>
    <album>Cha Cha De Amor</album>
    <album>Christmas and You</album>
    <album>Christmas Cocktail Tunes</album>
    <album>Christmas Crooners</album>
    <album>Christmas Crooners (The 50 Most Famous Xmas Carols and Songs Sung by Dean Martin, Nat King Cole, Frank Sinatra, Bing Crosby, Tino</album>
    <album>Christmas Crooners: The 50 Most Famous Xmas Carols and Songs Sung by Frank Sinatra, Bing Crosby, Dean Martin, Nat King Cole, Tino</album>
    <album>Christmas Decorating Playlist</album>
    <album>christmas songs to remind you of your childhood</album>
    <album>Christmas with 'The Broons'</album>
    <album>Christmas with Dean Martin</album>
    <album>Christmas With Dean Martin</album>
    <album>Christmas With Dino</album>
    <album>Christmas With Dino! A Dean Martin Christmas! (Remastered)</album>
    <album>Christmas with My Friends - Happy Holidays to You and Yours</album>
    <album>Christmas with the Mega Stars, Vol. 1</album>
    <album>Christmas With the Rat Pack</album>
    <album>Christmas With The Rat Pack</album>
    <album>Christmas With The Rat Pack (Frank Sinatra and Dean Martin)</album>
    <album>Christmas Wonderland</album>
    <album>Christmas World Hits & Internationale Stars</album>
    <album>Come Fly With Me</album>
    <album>Country Style</album>
    <album>Crooners at Christmas Time</album>
    <album>Cuddle Up By the Fireside</album>
    <album>Dean Martin</album>
    <album>Dean Martin - Everybody Loves Somebody</album>
    <album>Dean Martin - Gold Selection</album>
    <album>Dean Martin - Greatest Christmas Songs</album>
    <album>Dean Martin - Out Of My Mind</album>
    <album>Dean Martin - That's Amore</album>
    <album>Dean Martin - Volare</album>
    <album>Dean Martin -Two</album>
    <album>Dean Martin as Matt Helm Sings Songs from "The Silencers"</album>
    <album>Dean Martin Hits Again</album>
    <album>Dean Martin Selected Hits Vol. 1</album>
    <album>Dean Martin Selected Hits Vol. 11</album>
    <album>Dean Martin Selected Hits Vol. 12</album>
    <album>Dean Martin Selected Hits Vol. 3</album>
    <album>Dean Martin Selected Hits Vol. 9</album>
    <album>Dean Martin Sings</album>
    <album>Dean Martin the Classic Years</album>
    <album>Dean Martin, Baby, It's Cold Outside Vol. 2</album>
    <album>Dean Martin, Selección 5 Estrellas Black</album>
    <album>Dean Martin, Vol. 1</album>
    <album>Dean Martin, Vol. 2</album>
    <album>Dean Martin: Essential 10</album>
    <album>Dean Martin: Memories of the 50's, Vol. 2</album>
    <album>Dean Martin: Once Upon a Time, Vol. 1</album>
    <album>Dean Martin: Once Upon a Time, Vol. 2</album>
    <album>Dean Martin: Peg O' My Heart</album>
    <album>Dean Martin: The Capitol Recordings, Vol. 1 (1948-1950)</album>
    <album>Dean Martin: The Capitol Recordings, Vol. 11 (1960-1961)</album>
    <album>Dean Martin: The Capitol Recordings, Vol. 12 (1961)</album>
    <album>Dean Martin: The Capitol Recordings, Vol. 2 (1950-1951)</album>
    <album>Dean Martin: The Capitol Recordings, Vol. 3 (1951-1952)</album>
    <album>Dean Martin: The Capitol Recordings, Vol. 6 (1955-1956)</album>
    <album>Dean Martin: The Capitol Recordings, Vol. 7 (1956-1957)</album>
    <album>Dean Martin: The Capitol Recordings, Vol. 8 (1957-1958)</album>
    <album>Dean Martin: The Capitol Recordings, Vol. 9 (1958-1959)</album>
    <album>Dean Martin's Mambo Italiano</album>
    <album>Deep Purple</album>
    <album>Deluxe: Chansons de Noël, Vol.3</album>
    <album>Dinner with Dean Martin</album>
    <album>Dino</album>
    <album>Dino At The Sands Hotel, Las Vegas, 8th February 1964</album>
    <album>Dino Latino</album>
    <album>Dino: The Essential Dean Martin</album>
    <album>Down Memory Lane: The Crooners</album>
    <album>Dream with Dean</album>
    <album>Dreamer</album>
    <album>Dreaming, The Nightime Collection</album>
    <album>Eh Cumpari! Vol. 2</album>
    <album>Essential Dean Martin</album>
    <album>Essential Love Songs (Remastered)</album>
    <album>Everybody Loves Somebody</album>
    <album>Family Christmas Party Mix</album>
    <album>For the Good Times</album>
    <album>Forever Gold - Memories Are Made Of This</album>
    <album>Four Classic Albums Plus (This Is Dean Martin / Sleep Warm / This Time I'm Swingin / Dean Martin's Greatest) (Digitally Remastered</album>
    <album>French Style</album>
    <album>Gentle On My Mind</album>
    <album>Great Records Of The Decade: 50's Hits Vol. 1</album>
    <album>Greatest Hits</album>
    <album>Greatest Hits (Only Original Recordings)</album>
    <album>Greatest Hits (Remastered)</album>
    <album>Greatest Hits From The 1950's</album>
    <album>Greatest Hits of the 50's & 60's, Vol. 6</album>
    <album>Happy In Love</album>
    <album>Heart And Soul</album>
    <album>High Noon</album>
    <album>High Noon - 20 All Time Favourites</album>
    <album>Hits & Memories 24 All Time Favourites</album>
    <album>Hits of The Rat Pack Live (Live)</album>
    <album>Holiday Classics: Silent Night</album>
    <album>Houston</album>
    <album>I Take a Lot of Pride in What I Am</album>
    <album>In Napoli</album>
    <album>It's Beginning To Look A Lot Like Christmas (Stereo)</album>
    <album>It's Christmas Time with Dean Martin</album>
    <album>Italian Love Songs</album>
    <album>Italian Lovesongs</album>
    <album>Italienischer Abend</album>
    <album>Jazz Lounge: Smooth Jazz & Piano Bar to Chill (Remastered)</album>
    <album>Jingle Bells</album>
    <album>La Paloma: Dean Martin Va Latin</album>
    <album>Laid Back And Live</album>
    <album>Legends - Dean Martin</album>
    <album>Let It Snow</album>
    <album>Let It Snow, Let It Snow, Let It Snow</album>
    <album>Let It Snow! For Christmas</album>
    <album>Let It Snow! Let It Snow! Let It Snow!</album>
    <album>Let It Snow! Let It Snow! Let It Snow! (Cool Yule)</album>
    <album>Line Renaud au Casino de Paris</album>
    <album>Line Renaud: Grandes chansons</album>
    <album>LIVE Hits</album>
    <album>Live: Las Vegas 1962</album>
    <album>Loves Italia (Remastered)</album>
    <album>Mambo Italiano, 1956-1960</album>
    <album>Members Club</album>
    <album>Memories 50 Hits Original Remastered</album>
    <album>Memories Are Made of This</album>
    <album>Memories Are Made Of This</album>
    <album>Memories Are Made Of This (Digitally Remastered 2010)</album>
    <album>Memories Are Made of This: Live Recordings</album>
    <album>Memories Are Made Of This... The Best Of</album>
    <album>Memory Lane</album>
    <album>Merry Christmas</album>
    <album>Merry Christmas ! Les classiques de Noël par Frank Sinatra et ses amis</album>
    <album>Merry Christmas (28 Beautiful Christmas Songs)</album>
    <album>Merry Christmas (Famous Songs - Famous Artists)</album>
    <album>Merry Christmas with Dean Martin</album>
    <album>Millennium 1950-1954</album>
    <album>Mr Rifle, My Pony and Me / Cindy (From "Rio Bravo" Soundtrack)</album>
    <album>Music around the World by Dean Martin</album>
    <album>Music To Watch Girls Go By</album>
    <album>My Woman, My Woman, My Wife</album>
    <album>Nat & Dean Wish You A Merry Christmas</album>
    <album>Nightclub Jazz</album>
    <album>Noël Crooners</album>
    <album>Ocean's 11 vs The Rat Pack - Volume 2</album>
    <album>Ocean's 11 vs The Rat Pack - Volume 6</album>
    <album>On an Evening in Roma</album>
    <album>Once in a While</album>
    <album>Once Upon a Time</album>
    <album>One More Time</album>
    <album>Original Hits</album>
    <album>Original Songs Remixed for a New Century</album>
    <album>Platine, les 100 Tubes de la Variété Française</album>
    <album>Polvere di stelle (Versioni originali)</album>
    <album>Pretty Baby</album>
    <album>Rat Pack Christmas</album>
    <album>Remastered Classics, Vol. 222, Dean Martin, Pt. 2</album>
    <album>Reprise Rarities (Vol. 5)</album>
    <album>Return to Me</album>
    <album>Return To Me</album>
    <album>Return to Me (Essential Hits of This Generation)</album>
    <album>Rides Again</album>
    <album>Rio Bravo (Film score 1959)</album>
    <album>Rio Bravo (Original Motion Picture Soundtrack)</album>
    <album>Romance Italiano</album>
    <album>Silent Night</album>
    <album>Silent Night - Andy Williams & Friends</album>
    <album>Silver Bells</album>
    <album>Silver Bells - 100 Christmas Hits</album>
    <album>Silver Bells - Your Christmas Music Gift!</album>
    <album>Simply ... Dino! (2020 Remaster)</album>
    <album>Sittin' on Top of the World</album>
    <album>Six Pack: Christmas With Dean Martin - EP</album>
    <album>Sleep Warm</album>
    <album>Some Enchanted Evening</album>
    <album>Somewhere There's a Someone</album>
    <album>Songs from the Mojave Wasteland - Music as Heard in Fallout: New Vegas</album>
    <album>Super Fifties Christmas (Volume 2)</album>
    <album>Super Oldie Mix</album>
    <album>Superstar Files (75 Original Recordings)</album>
    <album>Sway</album>
    <album>Sway - The Singles 1946-1962</album>
    <album>Sway (The Rip-Off Artist Remix)</album>
    <album>Swingin' Down Yonder</album>
    <album>That's Amore</album>
    <album>That's Amore Baby! - The Great Hit Sounds Of Dean Martin</album>
    <album>That's Amore: The Best of Dean Martin</album>
    <album>That's Amore: The Best Of Dean Martin</album>
    <album>That's Amore!</album>
    <album>The Best of Dean Martin Vol. 3</album>
    <album>The Best Of Dino Vol. 1</album>
    <album>The Best Of Dino Vol. 2</album>
    <album>The Capitol Recordings Vol 2 (1950-1951)</album>
    <album>The Capitol Years</album>
    <album>The Casual Voice</album>
    <album>The Christmas Songs That Inspired Michael Buble</album>
    <album>The Dean Martin Christmas Album</album>
    <album>The Dean Martin Collection</album>
    <album>The Dean Martin Collection 1946-62</album>
    <album>The Dean Martin Show</album>
    <album>The Dean Martin TV Show</album>
    <album>The Door Is Still Open to My Heart</album>
    <album>The Essential Dean Martin</album>
    <album>The Essential of Dino</album>
    <album>The First Songs of Dino, Vol. 1</album>
    <album>The Great Dean Martin</album>
    <album>The Greatest Hits Collection - 40 Tracks Digitally Remastered</album>
    <album>The Hit Sound of Dean Martin</album>
    <album>The King of Cool - The Ultimate Dean Martin Collection Vol 2</album>
    <album>The King of Cool: The Ultimate Dean Martin Collection Volume 2</album>
    <album>The King of Cool: The Ultimate Dean Martin Collection Volume 3</album>
    <album>The King of Cool: The Ultimate Dean Martin Collection Volume 5</album>
    <album>The Kings of Christmas</album>
    <album>The Legendary Crooners - Dean Martin</album>
    <album>The Nashville Sessions</album>
    <album>The Platinum Collection</album>
    <album>The Playlist</album>
    <album>The Rat Pack - Cool Cat Classics</album>
    <album>The Rat Pack - The Collection</album>
    <album>The Rat Pack Live (Live)</album>
    <album>The Rat Pack: Live At The Sands</album>
    <album>The Rat Pack: Swinging with the Cool Cats Vol. 4</album>
    <album>The Ratpack 100 Hits</album>
    <album>The Reprise Years</album>
    <album>The Right Kind Of Town</album>
    <album>The Singles</album>
    <album>The Sound of Christmas, Vol. 1 - Christmas With the Rat Pack - Frank Sinatra & Dean Martin</album>
    <album>The Very Best of Dean Martin</album>
    <album>The Very Best Of Dean Martin</album>
    <album>The Very Best of Jazz - 50 Unforgettable Tracks (Remastered)</album>
    <album>The Very Best of Nancy & Frank Sinatra, Vol. 2</album>
    <album>The Voice / Dean Martin</album>
    <album>The Weather's Frightful</album>
    <album>This Is Dean Martin</album>
    <album>This Time I'm Swingin'</album>
    <album>To Marvelous For Words</album>
    <album>Too Cool Classic Hits of Dean Martin & Frank Sinatra</album>
    <album>Ultimate Hits - Russ Conway, Cliff Richard & Friends</album>
    <album>Ultra Lounge: Vegas Baby!</album>
    <album>Ultra-Lounge: Wild, Cool & Swingin' Volume Five</album>
    <album>Ultra-Lounge/Christmas Cocktails (Vol. 2)</album>
    <album>Unforgettable Dean Martin</album>
    <album>Vintage Music No. 134 - LP: Dean Martin</album>
    <album>Weihnachten 2024</album>
    <album>Welcome to My World</album>
    <album>Western Movie Themes</album>
    <album>When You're Smiling</album>
    <album>When You're Smiling, Vol. 1</album>
    <album>White Christmas</album>
    <album>White Christmas With Nat King Cole And Dean Martin</album>
    <album>Winter Wonderland: The Very Best of Holiday Jazz Classics by Duke Ellington, Frank Sinatra, Ella Fitzgerald, Bing Crosby, Sarah Va</album>
    <album>Xmas Classics - Essential Christmas Songs (Deluxe Special Edition)</album>
    <album>You're the Best Thing That Ever Happened to Me</album>
  </albums>
</artist>