<?xml version="1.0" encoding="UTF-8"?>
<artist>
  <name>Charles Brown</name>
  <albums>
    <album>All My Life</album>
    <album>An Introduction To Charles Brown</album>
    <album>Black Night</album>
    <album>Blues N' Brown</album>
    <album>Charles Brown Selected Hits Vol. 3</album>
    <album>Charles Brown Sings Christmas Songs</album>
    <album>Cryin' Mercy</album>
    <album>Devil's Blues</album>
    <album>In A Grand Style</album>
    <album>Just A Lucky So And So</album>
    <album>LEGENDARY BLUES VOL.13 (전설적인 블루스 모음집)</album>
    <album>Numero Uno Blues</album>
    <album>Please Come Home for Christmas</album>
    <album>Saga Blues: Cool Blues Singer</album>
    <album>So Goes Love</album>
    <album>Sunshine In My Life</album>
    <album>The Birth of R&B</album>
    <album>The Original Blues Sound</album>
    <album>Timeless Blues: Charles Brown</album>
    <album>Trouble Blues</album>
  </albums>
</artist>