<?xml version="1.0" encoding="UTF-8"?>
<artist>
  <name>The Shangri-Las</name>
  <albums>
    <album>'60s Pop Number 1's</album>
    <album>100 Greatest 60's Hits</album>
    <album>Eis am Stiel - Best Of</album>
    <album>Essential Classics, Vol. 534- The Shangri-las</album>
    <album>Essential Classics, Vol. 534: The Shangri-las</album>
    <album>Female Sounds of the Sixties</album>
    <album>Goodnight Sweet Dreams</album>
    <album>Goofy Greats</album>
    <album>Happy Days! - 22 Original Rock 'n' Roll Hits</album>
    <album>Here Comes the Girls: 1960s Pop Live Show</album>
    <album>Hits</album>
    <album>Holiday For Strings</album>
    <album>Leader Of The Pack</album>
    <album>Leader of the Pack, Vol. 2</album>
    <album>Paradise</album>
    <album>Past, Present and Future</album>
    <album>Remember (Hits and rarities from the bad girls of 60s pop)</album>
    <album>The Best Of The Shangri-Las</album>
    <album>The Complete Collection</album>
    <album>The Dave Cash Collection: 50th Anniversary of the Big L (Pirate Radio London), Vol. 1</album>
    <album>The Train From Kansas City</album>
    <album>The Very Best Of The Shangri-Las</album>
    <album>This is the Shangri-Las</album>
  </albums>
</artist>