<?xml version="1.0" encoding="UTF-8"?>
<artist>
  <name>Jimmy Jones</name>
  <albums>
    <album>Classic Hit Singles - Good Timin Jimmy Jones - Original Chart Toppers</album>
    <album>Fabulous 50s & 60s</album>
    <album>Feel The Spirit Of The 60's</album>
    <album>Golden Hits 1960-1961 with Petula Clark, Duane Eddy & Friends</album>
    <album>Good Timin'</album>
    <album>Good Timin' (Bonus Track Version)</album>
    <album>Greatest Hits</album>
    <album>Handy Man</album>
    <album>Handy Man - The Best of Jimmy Jones</album>
    <album>Handy Man - The Very Best Of</album>
    <album>He's Sure the Boy I Love - Remember When</album>
    <album>Jimmy Jones' Handy Man</album>
    <album>Leisure Time</album>
  </albums>
</artist>