<?xml version="1.0" encoding="UTF-8"?>
<artist>
  <name>Social Distortion</name>
  <albums>
    <album>Aguante El Punk Rock</album>
    <album>Ball and Chain EP</album>
    <album>Greatest Hits</album>
    <album>Hard Times And Nursery Rhymes (Deluxe Edition)</album>
    <album>Let It Be Me EP</album>
    <album>Live At The Roxy</album>
    <album>Mommy's Little Monster</album>
    <album>Sex, Love And Rock 'N' Roll</album>
    <album>Social Distortion</album>
    <album>Somewhere Between Heaven And Hell</album>
    <album>The Ultimate Skate Punk Album Vol.3</album>
    <album>White Light White Heat White Trash</album>
  </albums>
</artist>