<?xml version="1.0" encoding="UTF-8"?>
<artist>
  <name>Patrick Hernandez</name>
  <albums>
    <album>Born to Be Alive (Extended Version)</album>
    <album>Born to Be Alive (The Original Instrumental Version)</album>
    <album>Born to Be Alive (The Original)</album>
    <album>Born To Be Alive (The Remixes)</album>
    <album>Born to Be Alive (Unplugged & Reborn Versions)</album>
    <album>Born to be alive Snight B Remix</album>
    <album>Climax (Original Motion Picture Soundtrack)</album>
    <album>Patrick Hernandez The Album</album>
    <album>Tribute To The Funk</album>
    <album>Wog Boy 2 Original Soundtrack</album>
  </albums>
</artist>