<?xml version="1.0" encoding="UTF-8"?>
<artist>
  <name>Willie Nelson</name>
  <albums>
    <album>… Featuring Norah Jones</album>
    <album>100 Country Music Hits Vol. 1</album>
    <album>20 Country Classics</album>
    <album>A Beautiful Time</album>
    <album>A Horse Called Music</album>
    <album>Across The Borderline</album>
    <album>Across The Mornin' Sky (Live)</album>
    <album>Aimin' to Please (Bonus Track version)</album>
    <album>Always On My Mind</album>
    <album>America (Live)</album>
    <album>American Heartland, Vol. 1</album>
    <album>And Then I Wrote</album>
    <album>Angel Eyes</album>
    <album>At Midnight: Willie Nelson</album>
    <album>At The Boarding House</album>
    <album>Band of Brothers</album>
    <album>Banks Of The Old Bandera</album>
    <album>Been So Long (Live)</album>
    <album>Bluegrass</album>
    <album>Bob Dylan - 30th Anniversary Concert Celebration (Deluxe Edition Remastered)</album>
    <album>Boots, Buckles & Spurs - 50 Songs Celebrate 50 Years of Cowboy Tradition</album>
    <album>Both Sides Now</album>
    <album>Brand on My Heart</album>
    <album>Capitol Theater, Passaic, Nj. April 1st, 1979 (Remastered, Live On Broadcasting)</album>
    <album>Certified Hits</album>
    <album>Christmas with Michael W. Smith and Friends</album>
    <album>City Of New Orleans</album>
    <album>Country 100</album>
    <album>Country Classics</album>
    <album>Country Dance Party</album>
    <album>Country Essentials</album>
    <album>Country Favorites - Willie Nelson Style</album>
    <album>Country Greats</album>
    <album>Country Greats, Vol. 16</album>
    <album>Country Love</album>
    <album>Country Music</album>
    <album>Country Music for a Hearty Breakfast</album>
    <album>Country Outlaws</album>
    <album>Country Willie - His Own Songs</album>
    <album>Countryman</album>
    <album>Crazy</album>
    <album>Crazy - The Original Willie Nelson Album</album>
    <album>Django and Jimmie</album>
    <album>Down In Mexico</album>
    <album>Eclectic Funky Swamp Gems</album>
    <album>First Rose of Spring</album>
    <album>Flowin' From My Mind (Live Austin '74)</album>
    <album>For Real</album>
    <album>For the Good Times: A Tribute to Ray Price</album>
    <album>Forrest Gump - The Soundtrack</album>
    <album>Friendship</album>
    <album>Funny How Time Slips Away (with Faron Young)</album>
    <album>God's Problem Child</album>
    <album>Good Times</album>
    <album>Greatest Hits</album>
    <album>Greatest Hits (& Some That Will Be)</album>
    <album>Half Nelson</album>
    <album>Healing Hands Of Time</album>
    <album>Heartland (Live)</album>
    <album>Here We Go Again: Celebrating The Genius Of Ray Charles</album>
    <album>Here's Willie Nelson</album>
    <album>Heroes</album>
    <album>Highway Call (Live '79)</album>
    <album>Honeysuckle Rose - Music From The Original Soundtrack</album>
    <album>Hot Hundred Country</album>
    <album>I Don't Know A Thing About Love: The Songs of Harlan Howard</album>
    <album>I Let My Mind Wander</album>
    <album>I'll Love You Till The Day I Die</album>
    <album>I'm Not There (Music From The Motion Picture - Original Soundtrack)</album>
    <album>Imagine: John Lennon 75th Birthday Concert (Live)</album>
    <album>In the Jailhouse Now</album>
    <album>It Always Will Be</album>
    <album>Jack Johnson & Friends: Best Of Kokua Festival, A Benefit For The Kokua Hawaii Foundation</album>
    <album>Johnny Cash and The Royal Philharmonic Orchestra</album>
    <album>Just As I Am</album>
    <album>Last Leaf On The Tree</album>
    <album>Last Man Standing</album>
    <album>Last Of The Breed</album>
    <album>Lawless</album>
    <album>Laying My Burdens Down</album>
    <album>Legend: The Best Of Willie Nelson</album>
    <album>Life And Love</album>
    <album>Live at Billy Bob's Texas</album>
    <album>Live At Budokan</album>
    <album>Live at the Boarding House, San Francisco</album>
    <album>Live at the Capitol Theater, Passaic, New Jersey, 1979 - FM Radio Broadcast</album>
    <album>Live at the Philharmonic</album>
    <album>Live Country Music Concert</album>
    <album>Live Forever: A Tribute To Billy Joe Shaver</album>
    <album>Live From Austin, TX</album>
    <album>Live in Dallas 1994 Part Four (Live)</album>
    <album>Live in Dallas 1994 Part One (Live)</album>
    <album>Live in Dallas 1994 Part Two (Live)</album>
    <album>Live In Dallas, Texas, Kafm Radio, 1 July, 1976 (Remastered)</album>
    <album>Live in Houston 1984 Part One (Live)</album>
    <album>Live in Texas 1984 Part Four (Live)</album>
    <album>Live in Texas 1984 Part One (Live)</album>
    <album>Live in Texas 1984 Part Three (Live)</album>
    <album>Live in Texas 1984 Part Two (Live)</album>
    <album>Long Story Short: Willie Nelson 90 (Live At The Hollywood Bowl)</album>
    <album>Lost And Found</album>
    <album>Lost Highway</album>
    <album>Love Songs 02</album>
    <album>Made In Texas</album>
    <album>Make Way for Willie Nelson</album>
    <album>Me and Paul</album>
    <album>Milk Cow Blues</album>
    <album>Moment Of Forever</album>
    <album>Most Of All</album>
    <album>Mr. Record Man - The Early Singles As & BS</album>
    <album>Music from The American Epic Sessions (Deluxe)</album>
    <album>My Way</album>
    <album>Night Life - Willie Nelson</album>
    <album>Oh What A Beautiful World</album>
    <album>Oh What A Beautiful World (with Rodney Crowell)</album>
    <album>Old Friends</album>
    <album>Old Friends (Live)</album>
    <album>On The Road Again</album>
    <album>On The Road Again (Live)</album>
    <album>On The Road Again Vol 3</album>
    <album>On The Road Again: Willie Nelson Live</album>
    <album>On the road, On Air (live)</album>
    <album>On The Road, On Air (live)</album>
    <album>One Day At A Time (Live Denver '75)</album>
    <album>One For The Road</album>
    <album>One For The Road (with Leon Russell)</album>
    <album>Outlaw Country: Live From Austin, TX</album>
    <album>Outlaw: Celebrating the Music of Waylon Jennings (Live)</album>
    <album>Outlaws And Angels</album>
    <album>Partners</album>
    <album>Peace in the Valley</album>
    <album>Petty Country (A Country Music Celebration Of Tom Petty)</album>
    <album>Phases And Stages</album>
    <album>Poet: a Tribute to Townes Van Zandt</album>
    <album>Pure Country: Pure Heart (Original Motion Picture Soundtrack)</album>
    <album>Rainbow Connection</album>
    <album>Red Headed Stranger</album>
    <album>Red Headed Stranger (Expanded Edition)</album>
    <album>Red Headed Stranger (Live From Austin City Limits, 1976)</album>
    <album>Restoration: The Songs Of Elton John And Bernie Taupin</album>
    <album>Rhe Troubadour, West Hollywood, Ca. November 6th, 1975 (Remastered, Live On Broadcasting)</album>
    <album>Ride Me Back Home</album>
    <album>Run That By Me One More Time</album>
    <album>San Antonio Rose</album>
    <album>Setlist: The Very Best Of Willie Nelson LIVE</album>
    <album>Seventies Country Music</album>
    <album>Shotgun Willie</album>
    <album>Sing Me Back Home: The Music Of Merle Haggard (Live)</album>
    <album>Somewhere over the Rainbow</album>
    <album>Son of the South</album>
    <album>South of the Border</album>
    <album>Southern Jukebox</album>
    <album>Spirit</album>
    <album>Stardust</album>
    <album>Stars & Stripes - The Beach Boys</album>
    <album>Stars on Sunday - 20 Inspirational Favourites</album>
    <album>Step It Up And Go</album>
    <album>Stronger Than Most (Live)</album>
    <album>Summer Jazz Beats</album>
    <album>Summertime: Willie Nelson Sings Gershwin</album>
    <album>Take It To The Limit</album>
    <album>Texas In My Soul</album>
    <album>Texas Standards</album>
    <album>That's Life</album>
    <album>The Anthology</album>
    <album>The Best Of</album>
    <album>The Border</album>
    <album>The Christmas Album</album>
    <album>The Complete Atlantic Sessions</album>
    <album>The Early Years</album>
    <album>The Essential Highwaymen</album>
    <album>The Essential Willie Nelson</album>
    <album>The Great Divide</album>
    <album>The IRS Tapes: Who'll Buy My Memories</album>
    <album>The Last Letter</album>
    <album>The Music of Red Dead Redemption 2 (Original Soundtrack)</album>
    <album>The Party's Over</album>
    <album>The Promiseland</album>
    <album>The Sound In Your Mind</album>
    <album>The Texas Broadcast Collection 1994 (live)</album>
    <album>The Troublemaker</album>
    <album>The Ultimate Collection</album>
    <album>The Ultimate Collection (Deluxe Edition)</album>
    <album>The Ultimate Willie Collection</album>
    <album>The Willie Nelson Family</album>
    <album>The Willie Way</album>
    <album>The Winning Hand</album>
    <album>This Is Willie Nelson</album>
    <album>This Land Is Your Land: Songs Of Unity</album>
    <album>To All The Girls I've Loved Before</album>
    <album>To All The Girls...</album>
    <album>Together on Tour (Live)</album>
    <album>Tougher Than Leather</album>
    <album>Travelling, Vol. 2</album>
    <album>Twilight On The Trail</album>
    <album>Unbroken (Live)</album>
    <album>Various Artists - The Unforgettable Voices: 30 Best Of Willie Nelson & The Country Masters (MP3 Compilation)</album>
    <album>Volunteer Jam III & IV (Live)</album>
    <album>Vote 'Em Out</album>
    <album>Way Up High (Live 1981)</album>
    <album>What A Wonderful World</album>
    <album>What Love Can Do</album>
    <album>What Would You Take For Me</album>
    <album>White Rose Waltz</album>
    <album>Wildcat Mama</album>
    <album>Wilie Nelson, Vol. 1</album>
    <album>Willie And Family Live</album>
    <album>Willie and the Boys: Willie's Stash Vol. 2</album>
    <album>Willie and the Wheel</album>
    <album>Willie Nelson</album>
    <album>Willie Nelson - 16 Biggest Hits</album>
    <album>Willie Nelson - Summit Radio Broadcast Houston Texas 31st December 1984 Part Four.</album>
    <album>Willie Nelson - Summit Radio Broadcast Houston Texas 31st December 1984 Part One.</album>
    <album>Willie Nelson - Summit Radio Broadcast Houston Texas 31st December 1984 Part Three.</album>
    <album>Willie Nelson American Outlaw (Live)</album>
    <album>Willie Nelson And Family</album>
    <album>Willie Nelson And Friends</album>
    <album>Willie Nelson And Friends Live (Live)</album>
    <album>Willie Nelson and Leon Russell (Live)</album>
    <album>Willie Nelson Live</album>
    <album>Willie Nelson Live On Air vol. 1</album>
    <album>Willie Nelson Sings Kristofferson</album>
    <album>Willie Nelson The Collection</album>
    <album>Willie Nelson With Special Guest Curtis Potter (Original Step One Records Recordings)</album>
    <album>Willie Nelson: The Demos Project, Vol. One</album>
    <album>Willie Nelson: The Demos Project, Vol. Two</album>
    <album>Without A Song</album>
    <album>Words Don't Fit The Picture</album>
    <album>Yesterday's Wine</album>
    <album>You Don't Know Me: The Songs Of Cindy Walker</album>
    <album>You Were Always On My Mind</album>
    <album>舒活爵士</album>
  </albums>
</artist>